tfq0seo/__init__.py
tfq0seo/benchmark.py
tfq0seo/cli.py
tfq0seo/analyzers/__init__.py
tfq0seo/analyzers/content.py
tfq0seo/analyzers/links.py
tfq0seo/analyzers/performance.py
tfq0seo/analyzers/seo.py
tfq0seo/analyzers/technical.py
tfq0seo/core/__init__.py
tfq0seo/core/app.py
tfq0seo/core/config.py
tfq0seo/core/crawler.py
tfq0seo/core/report_optimizer.py
tfq0seo/exporters/__init__.py
tfq0seo/exporters/base.py
tfq0seo/templates/enhanced_report.html
tfq0seo/templates/optimized_report.html
tfq0seo/templates/report.html
tfq0seo-2.3.2.dist-info/licenses/LICENSE
tfq0seo-2.3.2.dist-info/METADATA
tfq0seo-2.3.2.dist-info/WHEEL
tfq0seo-2.3.2.dist-info/entry_points.txt
tfq0seo-2.3.2.dist-info/top_level.txt
tfq0seo-2.3.2.dist-info/RECORD
