Metadata-Version: 2.4
Name: tfq0seo
Version: 2.3.2
Summary: Fast SEO analysis tool with reports
Home-page: https://github.com/tfq0seo/tfq0seo
Author: TFQ0 SEO Team
License: MIT
Classifier: Development Status :: 4 - Beta
Classifier: Intended Audience :: Developers
Classifier: Topic :: Internet :: WWW/HTTP :: Site Management
Classifier: License :: OSI Approved :: MIT License
Classifier: Programming Language :: Python :: 3
Requires-Python: >=3.8
License-File: LICENSE
Requires-Dist: aiohttp>=3.8.0
Requires-Dist: beautifulsoup4>=4.11.0
Requires-Dist: click>=8.1.0
Requires-Dist: jinja2>=3.1.0
Requires-Dist: rich>=12.6.0
Requires-Dist: textstat>=0.7.3
Requires-Dist: validators>=0.20.0
Requires-Dist: pyyaml>=6.0
Requires-Dist: python-dateutil>=2.8.0
Requires-Dist: urllib3>=1.26.0
Requires-Dist: psutil>=5.9.0
Provides-Extra: full
Requires-Dist: lxml>=4.9.0; extra == "full"
Requires-Dist: openpyxl>=3.0.0; extra == "full"
Requires-Dist: pandas>=1.5.0; extra == "full"
Dynamic: home-page
Dynamic: license-file
Dynamic: requires-python
